newcodeex/__init__.py
newcodeex/example.py
newcodeex-1.0.dist-info/LICENCE.txt
newcodeex-1.0.dist-info/METADATA
newcodeex-1.0.dist-info/WHEEL
newcodeex-1.0.dist-info/top_level.txt
newcodeex-1.0.dist-info/RECORD
