Metadata-Version: 2.1
Name: newcodeex
Version: 1.0
Summary: example package
Home-page: UNKNOWN
Author: kamalika
Author-email: knath1989@gmail.com
License: UNKNOWN
Platform: UNKNOWN
